alto_tools/__init__.py
alto_tools/alto_tools.py
alto_tools-0.1.0.dist-info/LICENSE
alto_tools-0.1.0.dist-info/METADATA
alto_tools-0.1.0.dist-info/WHEEL
alto_tools-0.1.0.dist-info/entry_points.txt
alto_tools-0.1.0.dist-info/top_level.txt
alto_tools-0.1.0.dist-info/RECORD
