Metadata-Version: 2.1
Name: alto-tools
Version: 0.1.0
Summary: Perform various operations on ALTO xml files
Author: Clemens Neudecker
Project-URL: Homepage, https://github.com/cneud/alto-tools
Project-URL: Repository, https://github.com/cneud/alto-tools.git
Keywords: optical character recognition,digital libraries
Classifier: Development Status :: 4 - Beta
Classifier: Environment :: Console
Classifier: Intended Audience :: Science/Research
Classifier: Intended Audience :: Other Audience
Classifier: License :: OSI Approved :: Apache Software License
Classifier: Programming Language :: Python :: 3
Classifier: Programming Language :: Python :: 3 :: Only
Classifier: Topic :: Scientific/Engineering :: Information Analysis
Classifier: Topic :: Text Processing
Requires-Python: >=3.7
License-File: LICENSE
